msteams/__init__.py
msteams/plugin.py
sentry_msteams-0.8.0.dist-info/LICENSE
sentry_msteams-0.8.0.dist-info/METADATA
sentry_msteams-0.8.0.dist-info/WHEEL
sentry_msteams-0.8.0.dist-info/entry_points.txt
sentry_msteams-0.8.0.dist-info/top_level.txt
sentry_msteams-0.8.0.dist-info/RECORD
