Metadata-Version: 2.1
Name: sentry-msteams
Version: 0.8.0
Summary: A Sentry extension which posts notifications to Microsoft Teams (https://products.office.com/en-us/microsoft-teams/group-chat-software).
Home-page: https://github.com/Neko-Design/sentry-msteams
Author: Ewen McCahon
Author-email: hi@ewenmccahon.me
License: apache2
Platform: UNKNOWN
Classifier: Intended Audience :: Developers
Classifier: Intended Audience :: System Administrators
Classifier: Operating System :: OS Independent
Classifier: Topic :: Software Development
Requires-Dist: sentry
